<iati-activities xmlns:usg="https://foreignassistance.gov" generated-datetime="2024-12-31T15:25:44-05:00" version="2.03">
  <iati-activity default-currency="USD" hierarchy="1" last-updated-datetime="2024-12-31T12:57:06-05:00" xml:lang="en">
    <iati-identifier>US-GOV-11-70802</iati-identifier>
    <reporting-org ref="US-GOV-11" type="10">
      <narrative>Department of State</narrative>
    </reporting-org>
    <title>
      <narrative xml:lang="en">Africa Regional Democracy Fund (ARDF): Sao Tome Journalism Training for Elections and Human Rights Reporting</narrative>
    </title>
    <description type="1">
      <narrative xml:lang="en">Train both government and opposition-leaning print, radio, and television journalists to provide a higher level of professional reporting on elections, political activities, and human rights.</narrative>
    </description>
    <participating-org ref="1" role="1" type="10">
      <narrative>U.S. Agency for International Development</narrative>
    </participating-org>
    <participating-org ref="US-GOV-11" role="2" type="10">
      <narrative>Department of State</narrative>
    </participating-org>
    <participating-org ref="US-GOV-11" role="3" type="10">
      <narrative>Department of State</narrative>
    </participating-org>
    <participating-org ref="" role="4" type="10">
      <narrative>U.S. Government - Department of State</narrative>
    </participating-org>
    <activity-status code="3"/>
    <activity-date iso-date="2017-10-01" type="1">
      <narrative>Date unavailable. Calculated start date is the earliest transaction date</narrative>
    </activity-date>
    <activity-date iso-date="2017-10-01" type="2"/>
    <activity-date iso-date="2018-09-30" type="3">
      <narrative>Date unavailable. Calculated end date is the latest transaction date</narrative>
    </activity-date>
    <activity-date iso-date="2018-09-30" type="4"/>
    <contact-info type="1">
      <organisation>
        <narrative>Department of State</narrative>
      </organisation>
      <person-name>
        <narrative>Jenee Sharon; Wes Aviles; Ryan Boles</narrative>
      </person-name>
      <telephone>202-647-4000</telephone>
      <email>SharonJL@state.gov; AvilesWH@state.gov; rboles@usaid.gov</email>
      <website></website>
      <mailing-address>
        <narrative>2201 C St. NW, Washington, DC 20520</narrative>
      </mailing-address>
    </contact-info>
    <activity-scope code="5"/>
    <collaboration-type code="1"/>
    <default-flow-type code="10"/>
    <default-finance-type code="110"/>
    <default-aid-type code="C01"/>
    <default-tied-status code="4"/>
    <transaction ref="45EFD8041DE6">
      <transaction-type code="2"/>
      <transaction-date iso-date="2018-01-01"/>
      <value value-date="2018-01-01">84000</value>
      <description>
        <narrative>GLIDE: (COVID-19)</narrative>
      </description>
      <receiver-org type="10" ref="US-GOV-11">
        <narrative>U.S. Government - Department of State</narrative>
      </receiver-org>
      <disbursement-channel code="2"/>
      <sector code="10" vocabulary="99">
        <narrative>Civil Society</narrative>
      </sector>
      <sector code="15153" vocabulary="1">
        <narrative>Media and free flow of information</narrative>
      </sector>
      <recipient-country code="ST"/>
      <usg:treasury-account code="72x1037">Economic Support Fund
        <usg:fiscal-funding-year begin="" end=""/>
      </usg:treasury-account>
    </transaction>
    <conditions attached="0"/>
    <usg:tec1/>
  </iati-activity>
  <iati-activity default-currency="USD" hierarchy="1" last-updated-datetime="2024-12-31T12:59:16-05:00" xml:lang="en">
    <iati-identifier>US-GOV-11-SAO50023GR0028</iati-identifier>
    <reporting-org ref="US-GOV-11" type="10">
      <narrative>Department of State</narrative>
    </reporting-org>
    <title>
      <narrative xml:lang="en">FSSMP Korfball for an Egalitarian Society in STP</narrative>
    </title>
    <description type="1">
      <narrative xml:lang="en">BUILD 4 KORFBALL COURTS, PROVIDE EQUIPMENT AND TRAINING TO 16 PE TEACHERS AND FACILITATE MATCHES BETWEEN SCHOOLS. CONDUCT 7 SPEAKING ACTIVITIES ON CITIZENSHIP AND HUMAN RIGHTS AND DEVELOPMENT IN CONJUNCTION WITH THE ATHLETIC EVENTS.</narrative>
    </description>
    <participating-org ref="1" role="1" type="10">
      <narrative>U.S. Agency for International Development</narrative>
    </participating-org>
    <participating-org ref="US-GOV-11" role="2" type="10">
      <narrative>Department of State</narrative>
    </participating-org>
    <participating-org ref="US-GOV-11" role="3" type="10">
      <narrative>Department of State</narrative>
    </participating-org>
    <participating-org ref="" role="4" type="10">
      <narrative>Fundacao Solidariedade Social Minu Pague</narrative>
    </participating-org>
    <activity-status code="3"/>
    <activity-date iso-date="2022-10-01" type="1">
      <narrative>Date unavailable. Calculated start date is the earliest transaction date</narrative>
    </activity-date>
    <activity-date iso-date="2022-10-01" type="2"/>
    <activity-date iso-date="2024-04-25" type="3"/>
    <activity-date iso-date="2024-04-25" type="4"/>
    <contact-info type="1">
      <organisation>
        <narrative>Department of State</narrative>
      </organisation>
      <person-name>
        <narrative>Jenee Sharon; Wes Aviles; Ryan Boles</narrative>
      </person-name>
      <telephone>202-647-4000</telephone>
      <email>SharonJL@state.gov; AvilesWH@state.gov; rboles@usaid.gov</email>
      <website></website>
      <mailing-address>
        <narrative>2201 C St. NW, Washington, DC 20520</narrative>
      </mailing-address>
    </contact-info>
    <activity-scope code="5"/>
    <collaboration-type code="1"/>
    <default-flow-type code="10"/>
    <default-finance-type code="110"/>
    <default-aid-type code="C01"/>
    <default-tied-status code="5"/>
    <transaction ref="3C2A2B2BA5E0">
      <transaction-type code="2"/>
      <transaction-date iso-date="2023-09-28"/>
      <value value-date="2023-09-28">130000</value>
      <description>
        <narrative>GLIDE: (COVID-19)</narrative>
      </description>
      <receiver-org>
        <narrative>Fundacao Solidariedade Social Minu Pague</narrative>
      </receiver-org>
      <disbursement-channel code="2"/>
      <sector code="7" vocabulary="99">
        <narrative>Rule of Law and Human Rights</narrative>
      </sector>
      <sector code="15160" vocabulary="1">
        <narrative>Human rights</narrative>
      </sector>
      <recipient-country code="ST"/>
      <usg:treasury-account code="72x1037">Economic Support Fund
        <usg:fiscal-funding-year begin="" end=""/>
      </usg:treasury-account>
    </transaction>
    <transaction ref="CF0E38D44DAB">
      <transaction-type code="3"/>
      <transaction-date iso-date="2024-01-10"/>
      <value value-date="2024-01-10">35000</value>
      <description>
        <narrative>GLIDE: (COVID-19)</narrative>
      </description>
      <receiver-org>
        <narrative>Fundacao Solidariedade Social Minu Pague</narrative>
      </receiver-org>
      <disbursement-channel code="2"/>
      <sector code="7" vocabulary="99">
        <narrative>Rule of Law and Human Rights</narrative>
      </sector>
      <sector code="15160" vocabulary="1">
        <narrative>Human rights</narrative>
      </sector>
      <recipient-country code="ST"/>
      <usg:treasury-account code="72x1037">Economic Support Fund
        <usg:fiscal-funding-year begin="" end=""/>
      </usg:treasury-account>
    </transaction>
    <transaction ref="8918F527C1E0">
      <transaction-type code="3"/>
      <transaction-date iso-date="2024-04-25"/>
      <value value-date="2024-04-25">64848</value>
      <description>
        <narrative>GLIDE: (COVID-19)</narrative>
      </description>
      <receiver-org>
        <narrative>Fundacao Solidariedade Social Minu Pague</narrative>
      </receiver-org>
      <disbursement-channel code="2"/>
      <sector code="7" vocabulary="99">
        <narrative>Rule of Law and Human Rights</narrative>
      </sector>
      <sector code="15160" vocabulary="1">
        <narrative>Human rights</narrative>
      </sector>
      <recipient-country code="ST"/>
      <usg:treasury-account code="72x1037">Economic Support Fund
        <usg:fiscal-funding-year begin="" end=""/>
      </usg:treasury-account>
    </transaction>
    <conditions attached="0"/>
    <usg:tec1/>
  </iati-activity>
  <iati-activity default-currency="USD" hierarchy="1" last-updated-datetime="2024-12-31T12:59:54-05:00" xml:lang="en">
    <iati-identifier>US-GOV-11-SAO50023GR0019</iati-identifier>
    <reporting-org ref="US-GOV-11" type="10">
      <narrative>Department of State</narrative>
    </reporting-org>
    <title>
      <narrative xml:lang="en">FSSMP Project Grow</narrative>
    </title>
    <description type="1">
      <narrative xml:lang="en">FSSMP Project Grow</narrative>
    </description>
    <participating-org ref="1" role="1" type="10">
      <narrative>U.S. Agency for International Development</narrative>
    </participating-org>
    <participating-org ref="US-GOV-11" role="2" type="10">
      <narrative>Department of State</narrative>
    </participating-org>
    <participating-org ref="US-GOV-11" role="3" type="10">
      <narrative>Department of State</narrative>
    </participating-org>
    <participating-org ref="" role="4" type="10">
      <narrative>Fundacao Solidariedade Social Minu Pague</narrative>
    </participating-org>
    <activity-status code="3"/>
    <activity-date iso-date="2022-10-01" type="1">
      <narrative>Date unavailable. Calculated start date is the earliest transaction date</narrative>
    </activity-date>
    <activity-date iso-date="2022-10-01" type="2"/>
    <activity-date iso-date="2023-12-21" type="3"/>
    <activity-date iso-date="2023-12-21" type="4"/>
    <contact-info type="1">
      <organisation>
        <narrative>Department of State</narrative>
      </organisation>
      <person-name>
        <narrative>Jenee Sharon; Wes Aviles; Ryan Boles</narrative>
      </person-name>
      <telephone>202-647-4000</telephone>
      <email>SharonJL@state.gov; AvilesWH@state.gov; rboles@usaid.gov</email>
      <website></website>
      <mailing-address>
        <narrative>2201 C St. NW, Washington, DC 20520</narrative>
      </mailing-address>
    </contact-info>
    <activity-scope code="5"/>
    <collaboration-type code="1"/>
    <default-flow-type code="10"/>
    <default-finance-type code="110"/>
    <default-aid-type code="C01"/>
    <default-tied-status code="5"/>
    <transaction ref="C4BA24F47DCE">
      <transaction-type code="2"/>
      <transaction-date iso-date="2023-09-28"/>
      <value value-date="2023-09-28">10000</value>
      <description>
        <narrative>GLIDE: (COVID-19)</narrative>
      </description>
      <receiver-org>
        <narrative>Fundacao Solidariedade Social Minu Pague</narrative>
      </receiver-org>
      <disbursement-channel code="2"/>
      <sector code="49" vocabulary="99">
        <narrative>Economic Development - General</narrative>
      </sector>
      <sector code="15110" vocabulary="1">
        <narrative>Public sector policy and administrative management</narrative>
      </sector>
      <recipient-country code="ST"/>
      <usg:treasury-account code="72x1037">Economic Support Fund
        <usg:fiscal-funding-year begin="" end=""/>
      </usg:treasury-account>
    </transaction>
    <transaction ref="B638A9B837E1">
      <transaction-type code="3"/>
      <transaction-date iso-date="2023-12-21"/>
      <value value-date="2023-12-21">10000</value>
      <description>
        <narrative>GLIDE: (COVID-19)</narrative>
      </description>
      <receiver-org>
        <narrative>Fundacao Solidariedade Social Minu Pague</narrative>
      </receiver-org>
      <disbursement-channel code="2"/>
      <sector code="49" vocabulary="99">
        <narrative>Economic Development - General</narrative>
      </sector>
      <sector code="15110" vocabulary="1">
        <narrative>Public sector policy and administrative management</narrative>
      </sector>
      <recipient-country code="ST"/>
      <usg:treasury-account code="72x1037">Economic Support Fund
        <usg:fiscal-funding-year begin="" end=""/>
      </usg:treasury-account>
    </transaction>
    <conditions attached="0"/>
    <usg:tec1/>
  </iati-activity>
</iati-activities>