{"author": null, "author_email": "aidtransparency@usaid.gov", "creator_user_id": "cd77289a-2ac8-4e91-adad-cb2bd09ca710", "id": "647eb99e-f06c-4aef-92a1-cec6bd852d53", "isopen": true, "license_id": "cc-zero", "license_title": "Creative Commons CCZero", "license_url": "http://www.opendefinition.org/licenses/cc-zero", "maintainer": null, "maintainer_email": null, "metadata_created": "2023-01-26T16:19:11.110336", "metadata_modified": "2024-12-28T00:10:36.607770", "name": "iaf-panama", "notes": "U.S Inter-American Foundation activities in Panama", "num_resources": 1, "num_tags": 0, "organization": {"id": "463819c5-39db-4986-baed-3720f393ba8f", "name": "iaf", "title": "Inter-American Foundation", "type": "organization", "description": "", "image_url": "https://www.iaf.gov/wp-content/uploads/2021/06/iaf-logo-large-600x165.png", "created": "2022-05-25T17:08:20.990019", "is_organization": true, "approval_status": "approved", "state": "active"}, "owner_org": "463819c5-39db-4986-baed-3720f393ba8f", "private": false, "state": "active", "title": "IAF - Panama", "type": "dataset", "url": null, "version": null, "extras": [{"key": "activity_count", "value": "77"}, {"key": "country", "value": ""}, {"key": "data_updated", "value": "2024-12-27 14:46:12"}, {"key": "filetype", "value": "activity"}, {"key": "iati_version", "value": "2.03"}, {"key": "language", "value": "English"}, {"key": "secondary_publisher", "value": ""}, {"key": "validation_status", "value": "Success"}], "resources": [{"cache_last_updated": null, "cache_url": null, "created": "2023-01-26T16:19:11.117205", "description": null, "format": "IATI-XML", "hash": "f83184d501e7005b6da1e4daa4a9b2acbb7791f0", "id": "cd62e8df-4687-49f0-9519-5a4991cd861a", "last_modified": null, "metadata_modified": "2024-12-28T00:10:36.613851", "mimetype": "", "mimetype_inner": null, "name": null, "package_id": "647eb99e-f06c-4aef-92a1-cec6bd852d53", "position": 0, "resource_type": null, "size": 314476, "state": "active", "url": "https://iati-reporting.s3.amazonaws.com/inter-american_foundation/xml/iati-activities-Panama.xml", "url_type": null}], "tags": [], "groups": [], "relationships_as_subject": [], "relationships_as_object": []}