<iati-activities xmlns:usg="https://foreignassistance.gov" generated-datetime="2024-12-27T14:46:46+00:00" version="2.03">
  <iati-activity default-currency="USD" hierarchy="1" last-updated-datetime="2024-12-27T14:46:15+00:00" xml:lang="en">
    <iati-identifier>US-GOV-12-1131PL20GH31145-124263</iati-identifier>
    <reporting-org ref="US-GOV-12" type="10">
      <narrative>Trade and Development Agency</narrative>
    </reporting-org>
    <title>
      <narrative xml:lang="en">PPL ICT Strategy Roadmap, through Enterprise - United States Unknown</narrative>
    </title>
    <description type="1">
      <narrative xml:lang="en">This grant funds technical assistance for PNG Power Limited (PPL), a state-owned electric utility in Papua New Guinea, to develop a roadmap for a fully integrated information and communications technology (ICT) platform. This roadmap would develop specifications and an implementation plan for deploying a smart metering system, communications network components and all major sub-systems comprising its ICT infrastructure, which is expected to lead to improved quality of service.</narrative>
    </description>
    <participating-org ref="2" role="1" type="10">
      <narrative>Department of State</narrative>
    </participating-org>
    <participating-org ref="US-GOV-12" role="2" type="10">
      <narrative>Trade and Development Agency</narrative>
    </participating-org>
    <participating-org ref="US-GOV-12" role="3" type="10">
      <narrative>Trade and Development Agency</narrative>
    </participating-org>
    <participating-org ref="" role="4" type="10">
      <narrative>Enterprise - United States Other</narrative>
    </participating-org>
    <activity-status code="3"/>
    <activity-date iso-date="2019-10-01" type="1">
      <narrative>Date unavailable. Calculated start date is the earliest transaction date</narrative>
    </activity-date>
    <activity-date iso-date="2019-10-01" type="2"/>
    <activity-date iso-date="2024-07-24" type="3"/>
    <activity-date iso-date="2024-07-24" type="4"/>
    <contact-info type="1">
      <organisation>
        <narrative>Trade and Development Agency</narrative>
      </organisation>
      <person-name>
        <narrative>Amy Swers and Liz Sutton; Ryan Boles</narrative>
      </person-name>
      <telephone>703-875-4357</telephone>
      <email>aswers@ustda.gov; esutton@ustda.gov; rboles@usaid.gov</email>
      <website></website>
      <mailing-address>
        <narrative>1101 Wilson Blvd. Suite 1100, Arlington, VA, 22209</narrative>
      </mailing-address>
    </contact-info>
    <activity-scope code="5"/>
    <collaboration-type code="1"/>
    <default-flow-type code="10"/>
    <default-finance-type code="110"/>
    <default-aid-type code="D02"/>
    <default-tied-status code="4"/>
    <transaction ref="0E85BF5114C9">
      <transaction-type code="2"/>
      <transaction-date iso-date="2020-07-24"/>
      <value value-date="2020-07-24">756175</value>
      <description>
        <narrative>GLIDE: (COVID-19)</narrative>
      </description>
      <receiver-org type="70" ref="XM-DAC-61000">
        <narrative>Enterprise - United States Other</narrative>
      </receiver-org>
      <disbursement-channel code="2"/>
      <sector code="28" vocabulary="99">
        <narrative>Infrastructure</narrative>
      </sector>
      <sector code="99810" vocabulary="1">
        <narrative>Sectors not specified</narrative>
      </sector>
      <recipient-country code="PG"/>
      <usg:treasury-account code="19x0113">Department of State, Diplomatic and Consular Programs
        <usg:fiscal-funding-year begin="" end=""/>
      </usg:treasury-account>
    </transaction>
    <conditions attached="0"/>
    <usg:tec1>
      <narrative>756,175</narrative>
    </usg:tec1>
  </iati-activity>
  <iati-activity default-currency="USD" hierarchy="1" last-updated-datetime="2024-12-27T14:46:15+00:00" xml:lang="en">
    <iati-identifier>US-GOV-12-1131PL20GH31145-128137</iati-identifier>
    <reporting-org ref="US-GOV-12" type="10">
      <narrative>Trade and Development Agency</narrative>
    </reporting-org>
    <title>
      <narrative xml:lang="en">Technical Assistance - Papua New Guinea Power Limited Information Communications Technology Strategy Roadmap Technical Assistance, through EnerNex</narrative>
    </title>
    <description type="1">
      <narrative xml:lang="en">This grant funds technical assistance for Papua New Guinea (PNG) Power Limited (PPL), a state-owned electric utility in Papua New Guinea, to develop a roadmap for a fully integrated information and communications technology (ICT) platform. This roadmap would develop specifications and an implementation plan for deploying a smart metering system, communications network components and all major sub-systems comprising its ICT infrastructure, which is expected to lead to improved quality of service.</narrative>
    </description>
    <participating-org ref="2" role="1" type="10">
      <narrative>Department of State</narrative>
    </participating-org>
    <participating-org ref="US-GOV-12" role="2" type="10">
      <narrative>Trade and Development Agency</narrative>
    </participating-org>
    <participating-org ref="US-GOV-12" role="3" type="10">
      <narrative>Trade and Development Agency</narrative>
    </participating-org>
    <participating-org ref="" role="4" type="10">
      <narrative>EnerNex</narrative>
    </participating-org>
    <activity-status code="3"/>
    <activity-date iso-date="2022-10-01" type="1">
      <narrative>Date unavailable. Calculated start date is the earliest transaction date</narrative>
    </activity-date>
    <activity-date iso-date="2022-10-01" type="2"/>
    <activity-date iso-date="2024-07-24" type="3"/>
    <activity-date iso-date="2024-07-24" type="4"/>
    <contact-info type="1">
      <organisation>
        <narrative>Trade and Development Agency</narrative>
      </organisation>
      <person-name>
        <narrative>Amy Swers and Liz Sutton; Ryan Boles</narrative>
      </person-name>
      <telephone>703-875-4357</telephone>
      <email>aswers@ustda.gov; esutton@ustda.gov; rboles@usaid.gov</email>
      <website></website>
      <mailing-address>
        <narrative>1101 Wilson Blvd. Suite 1100, Arlington, VA, 22209</narrative>
      </mailing-address>
    </contact-info>
    <activity-scope code="5"/>
    <collaboration-type code="1"/>
    <default-flow-type code="10"/>
    <default-finance-type code="110"/>
    <default-aid-type code="D02"/>
    <default-tied-status code="4"/>
    <transaction ref="C361041BCBA6">
      <transaction-type code="3"/>
      <transaction-date iso-date="2023-05-01"/>
      <value value-date="2023-05-01">264661</value>
      <description>
        <narrative>GLIDE: (COVID-19)</narrative>
      </description>
      <receiver-org>
        <narrative>EnerNex</narrative>
      </receiver-org>
      <disbursement-channel code="2"/>
      <sector code="28" vocabulary="99">
        <narrative>Infrastructure</narrative>
      </sector>
      <sector code="23630" vocabulary="1">
        <narrative>Electric power transmission and distribution (centralised grids)</narrative>
      </sector>
      <recipient-country code="PG"/>
      <usg:treasury-account code="19x0113">Department of State, Diplomatic and Consular Programs
        <usg:fiscal-funding-year begin="" end=""/>
      </usg:treasury-account>
    </transaction>
    <conditions attached="0"/>
    <usg:tec1>
      <narrative>2,268,525</narrative>
    </usg:tec1>
  </iati-activity>
  <iati-activity default-currency="USD" hierarchy="1" last-updated-datetime="2024-12-27T14:46:15+00:00" xml:lang="en">
    <iati-identifier>US-GOV-12-1131PL20GH31145-128136</iati-identifier>
    <reporting-org ref="US-GOV-12" type="10">
      <narrative>Trade and Development Agency</narrative>
    </reporting-org>
    <title>
      <narrative xml:lang="en">Technical Assistance - Papua New Guinea Power Limited Information Communications Technology Strategy Roadmap Technical Assistance, through EnerNex</narrative>
    </title>
    <description type="1">
      <narrative xml:lang="en">This grant funds technical assistance for PNG Power Limited (PPL), a state-owned electric utility in Papua New Guinea, to develop a roadmap for a fully integrated information and communications technology (ICT) platform. This roadmap would develop specifications and an implementation plan for deploying a smart metering system, communications network components and all major sub-systems comprising its ICT infrastructure, which is expected to lead to improved quality of service.</narrative>
    </description>
    <participating-org ref="2" role="1" type="10">
      <narrative>Department of State</narrative>
    </participating-org>
    <participating-org ref="US-GOV-12" role="2" type="10">
      <narrative>Trade and Development Agency</narrative>
    </participating-org>
    <participating-org ref="US-GOV-12" role="3" type="10">
      <narrative>Trade and Development Agency</narrative>
    </participating-org>
    <participating-org ref="" role="4" type="10">
      <narrative>EnerNex</narrative>
    </participating-org>
    <activity-status code="3"/>
    <activity-date iso-date="2021-10-01" type="1">
      <narrative>Date unavailable. Calculated start date is the earliest transaction date</narrative>
    </activity-date>
    <activity-date iso-date="2021-10-01" type="2"/>
    <activity-date iso-date="2024-07-24" type="3"/>
    <activity-date iso-date="2024-07-24" type="4"/>
    <contact-info type="1">
      <organisation>
        <narrative>Trade and Development Agency</narrative>
      </organisation>
      <person-name>
        <narrative>Amy Swers and Liz Sutton; Ryan Boles</narrative>
      </person-name>
      <telephone>703-875-4357</telephone>
      <email>aswers@ustda.gov; esutton@ustda.gov; rboles@usaid.gov</email>
      <website></website>
      <mailing-address>
        <narrative>1101 Wilson Blvd. Suite 1100, Arlington, VA, 22209</narrative>
      </mailing-address>
    </contact-info>
    <activity-scope code="5"/>
    <collaboration-type code="1"/>
    <default-flow-type code="10"/>
    <default-finance-type code="110"/>
    <default-aid-type code="D02"/>
    <default-tied-status code="4"/>
    <transaction ref="D7DA56B0FC84">
      <transaction-type code="3"/>
      <transaction-date iso-date="2022-08-24"/>
      <value value-date="2022-08-24">75618</value>
      <description>
        <narrative>GLIDE: (COVID-19)</narrative>
      </description>
      <receiver-org>
        <narrative>EnerNex</narrative>
      </receiver-org>
      <disbursement-channel code="2"/>
      <sector code="28" vocabulary="99">
        <narrative>Infrastructure</narrative>
      </sector>
      <sector code="23630" vocabulary="1">
        <narrative>Electric power transmission and distribution (centralised grids)</narrative>
      </sector>
      <recipient-country code="PG"/>
      <usg:treasury-account code="19x0113">Department of State, Diplomatic and Consular Programs
        <usg:fiscal-funding-year begin="" end=""/>
      </usg:treasury-account>
    </transaction>
    <conditions attached="0"/>
    <usg:tec1>
      <narrative>756,175</narrative>
    </usg:tec1>
  </iati-activity>
</iati-activities>